batch_nl/__init__.py
batch_nl/neighbourlist.py
batch_nl_torch-0.1.1.dist-info/licenses/LICENSE
batch_nl_torch-0.1.1.dist-info/METADATA
batch_nl_torch-0.1.1.dist-info/WHEEL
batch_nl_torch-0.1.1.dist-info/top_level.txt
batch_nl_torch-0.1.1.dist-info/RECORD
