Metadata-Version: 2.4
Name: batch_nl_torch
Version: 0.1.1
Summary: Efficient and batched PyTorch-based neighbour list builder for atomistic simulations
Author: Venkat Kapil
License-Expression: Apache-2.0
Project-URL: Homepage, https://github.com/venkatkapil24/batch_nl
Project-URL: Repository, https://github.com/venkatkapil24/batch_nl
Requires-Python: >=3.7
License-File: LICENSE
Requires-Dist: torch>=1.12
Requires-Dist: ase
Requires-Dist: matscipy
Dynamic: license-file
